djangobot/__init__.py
djangobot/cli.py
djangobot/client.py
djangobot/slack.py
djangobot-0.1.dist-info/DESCRIPTION.rst
djangobot-0.1.dist-info/METADATA
djangobot-0.1.dist-info/RECORD
djangobot-0.1.dist-info/WHEEL
djangobot-0.1.dist-info/entry_points.txt
djangobot-0.1.dist-info/metadata.json
djangobot-0.1.dist-info/top_level.txt
