Metadata-Version: 2.0
Name: djangobot
Version: 0.1
Summary: Bridge between Slack and Channels-based Django apps
Home-page: https://github.com/djangobot/djangobot
Author: Scott Burns
Author-email: scott.s.burns@gmail.com
License: MIT
Platform: UNKNOWN
Requires-Dist: autobahn (>=0.13.0)
Requires-Dist: channels (>=0.10.3)
Requires-Dist: pyopenssl (>=16.0.0)
Requires-Dist: requests (>=2.3.1)
Requires-Dist: twisted (>=16.0.0)
